{
    "$schema": "https://vega.github.io/schema/vega-lite/v5.json",
    "data": {
        "url": "https://api.beta.ons.gov.uk/v1/data?uri=/economy/nationalaccounts/balanceofpayments/timeseries/ikbi/mret",
        "format": {
            "property": "years"
        }
    },
    "title": "Imports",
    "width": 200,
    "height": 200,
    "mark": "line",
    "encoding": {
        "x": {
            "field": "date",
            "type": "temporal"
        },
        "y": {
            "field": "value",
            "type": "quantitative"
        }
    },
    "config": {}
}